auth/__init__.py
auth/__main__.py
auth/api.py
auth/helper.py
auth/parsers/__init__.py
auth/parsers/base.py
auth/parsers/helper.py
auth/parsers/token.py
jina_auth-0.2.2.dist-info/LICENSE
jina_auth-0.2.2.dist-info/METADATA
jina_auth-0.2.2.dist-info/WHEEL
jina_auth-0.2.2.dist-info/entry_points.txt
jina_auth-0.2.2.dist-info/top_level.txt
jina_auth-0.2.2.dist-info/RECORD
