Metadata-Version: 2.1
Name: jina-auth
Version: 0.2.2
Summary: A CLI for you to login in to Jina Ecosystem
Home-page: https://github.com/jina-ai/auth
Download-URL: https://github.com/jina-ai/auth/tags
Author: Jina AI
Author-email: hello@jina.ai
License: Apache 2.0
Project-URL: Documentation, https://github.com/jina-ai/auth/
Project-URL: Source, https://github.com/jina-ai/auth/
Project-URL: Tracker, https://github.com/jina-ai/auth/issues
Keywords: jina auth login logout user
Classifier: Development Status :: 3 - Alpha
Classifier: Intended Audience :: Developers
Classifier: Intended Audience :: Education
Classifier: Intended Audience :: Science/Research
Classifier: Programming Language :: Python :: 3.7
Classifier: Programming Language :: Python :: 3.8
Classifier: Programming Language :: Python :: 3.9
Classifier: Programming Language :: Python :: 3.10
Classifier: Programming Language :: Unix Shell
Classifier: Environment :: Console
Classifier: License :: OSI Approved :: Apache Software License
Classifier: Operating System :: OS Independent
Classifier: Topic :: Database :: Database Engines/Servers
Classifier: Topic :: Scientific/Engineering :: Artificial Intelligence
Classifier: Topic :: Internet :: WWW/HTTP :: Indexing/Search
Classifier: Topic :: Scientific/Engineering :: Image Recognition
Classifier: Topic :: Multimedia :: Video
Classifier: Topic :: Scientific/Engineering
Classifier: Topic :: Scientific/Engineering :: Mathematics
Classifier: Topic :: Software Development
Classifier: Topic :: Software Development :: Libraries
Classifier: Topic :: Software Development :: Libraries :: Python Modules
License-File: LICENSE
Requires-Dist: jina-hubble-sdk (>=0.9.2)
Provides-Extra: test
Requires-Dist: pytest ; extra == 'test'
Requires-Dist: pytest-timeout ; extra == 'test'
Requires-Dist: pytest-mock ; extra == 'test'
Requires-Dist: pytest-cov ; extra == 'test'
Requires-Dist: pytest-repeat ; extra == 'test'
Requires-Dist: pytest-reraise ; extra == 'test'
Requires-Dist: mock ; extra == 'test'
Requires-Dist: pytest-custom-exit-code ; extra == 'test'
Requires-Dist: black (==22.3.0) ; extra == 'test'
Requires-Dist: jina ; extra == 'test'
Requires-Dist: flake8 ; extra == 'test'
Requires-Dist: isort ; extra == 'test'
